{
    "data": [
        {
            "mem": 0,
            "val": "h"
        },
        {
            "mem": 1,
            "val": "i"
        },
        {
            "mem": 2,
            "val": ","
        },
        {
            "mem": 3,
            "val": " "
        },
        {
            "mem": 4,
            "val": "0"
        },
        {
            "mem": 5,
            "val": "8"
        },
        {
            "mem": 6,
            "val": "5"
        },
        {
            "mem": 7,
            "val": "a"
        },
        {
            "mem": 8,
            "val": "z"
        },
        {
            "mem": 9,
            "val": "a"
        },
        {
            "mem": 10,
            "val": "z"
        },
        {
            "mem": 11,
            "val": "a"
        },
        {
            "mem": 15,
            "val": "0"
        }
    ],
    "ops": [
        {
            "inx": 0,
            "cmd": "LD",
            "arg": "0"
        },
        {
            "inx": 1,
            "cmd": "ADD",
            "arg": "4"
        },
        {
            "inx": 2,
            "cmd": "ST",
            "arg": "5"
        },
        {
            "inx": 3,
            "cmd": "OUTR",
            "arg": "6"
        },
        {
            "inx": 4,
            "cmd": "INR",
            "arg": "11"
        },
        {
            "inx": 5,
            "cmd": "HLT",
            "arg": ""
        },
        {
            "inx": 6,
            "cmd": "LD",
            "arg": ""
        },
        {
            "inx": 7,
            "cmd": "OUT",
            "arg": ""
        },
        {
            "inx": 8,
            "cmd": "LD",
            "arg": "7"
        },
        {
            "inx": 9,
            "cmd": "OUT",
            "arg": ""
        },
        {
            "inx": 10,
            "cmd": "IRET",
            "arg": ""
        },
        {
            "inx": 11,
            "cmd": "IN",
            "arg": ""
        },
        {
            "inx": 12,
            "cmd": "ST",
            "arg": "5"
        },
        {
            "inx": 13,
            "cmd": "IRET",
            "arg": ""
        }
    ]
}